netbox_ipv4_tools/__init__.py
netbox_ipv4_tools/navigation.py
netbox_ipv4_tools/urls.py
netbox_ipv4_tools/views.py
netbox_ipv4_tools/static/netbox_ipv4_tools/js/netmask.js
netbox_ipv4_tools/static/netbox_ipv4_tools/js/range.js
netbox_ipv4_tools/static/netbox_ipv4_tools/js/supernet.js
netbox_ipv4_tools/templates/netbox_ipv4_tools/cidr-to-range.html
netbox_ipv4_tools/templates/netbox_ipv4_tools/cidr.html
netbox_ipv4_tools/templates/netbox_ipv4_tools/supernet-calculator.html
netbox_ipv4_tools-1.0.4.dist-info/LICENSE
netbox_ipv4_tools-1.0.4.dist-info/METADATA
netbox_ipv4_tools-1.0.4.dist-info/WHEEL
netbox_ipv4_tools-1.0.4.dist-info/top_level.txt
netbox_ipv4_tools-1.0.4.dist-info/RECORD
