Metadata-Version: 2.1
Name: netbox-ipv4-tools
Version: 1.0.4
Summary: Work with ipv4 in NetBox
Home-page: https://github.com/mlongo4290/netbox-ipv4-tools
Author: Michael Longo
License: Apache 2.0
Project-URL: Source, https://github.com/mlongo4290/netbox-ipv4-tools
Keywords: netbox-plugin
Classifier: Programming Language :: Python
Classifier: Programming Language :: Python :: 3
Classifier: Programming Language :: Python :: 3 :: Only
License-File: LICENSE
